pymodaq_plugins_thorlabs/__init__.py
pymodaq_plugins_thorlabs/utils.py
pymodaq_plugins_thorlabs/daq_move_plugins/__init__.py
pymodaq_plugins_thorlabs/daq_move_plugins/daq_move_BrushlessDCMotor.py
pymodaq_plugins_thorlabs/daq_move_plugins/daq_move_DCServoKCube.py
pymodaq_plugins_thorlabs/daq_move_plugins/daq_move_DCServoTCube.py
pymodaq_plugins_thorlabs/daq_move_plugins/daq_move_Elliptec.py
pymodaq_plugins_thorlabs/daq_move_plugins/daq_move_ElliptecPyMeasure.py
pymodaq_plugins_thorlabs/daq_move_plugins/daq_move_KPZ101.py
pymodaq_plugins_thorlabs/daq_move_plugins/daq_move_KinesisFlipper.py
pymodaq_plugins_thorlabs/daq_move_plugins/daq_move_KinesisIntegratedStepper.py
pymodaq_plugins_thorlabs/daq_move_plugins/daq_move_MFF101_pylablib.py
pymodaq_plugins_thorlabs/daq_move_plugins/daq_move_PRM1Z8_pylablib.py
pymodaq_plugins_thorlabs/daq_viewer_plugins/__init__.py
pymodaq_plugins_thorlabs/daq_viewer_plugins/plugins_0D/__init__.py
pymodaq_plugins_thorlabs/daq_viewer_plugins/plugins_0D/daq_0Dviewer_Kinesis_KPA101.py
pymodaq_plugins_thorlabs/daq_viewer_plugins/plugins_0D/daq_0Dviewer_TLPMPowermeter.py
pymodaq_plugins_thorlabs/daq_viewer_plugins/plugins_1D/__init__.py
pymodaq_plugins_thorlabs/daq_viewer_plugins/plugins_1D/daq_1Dviewer_CCSXXX.py
pymodaq_plugins_thorlabs/daq_viewer_plugins/plugins_2D/__init__.py
pymodaq_plugins_thorlabs/daq_viewer_plugins/plugins_2D/daq_2Dviewer_Thorlabs_DCx.py
pymodaq_plugins_thorlabs/daq_viewer_plugins/plugins_2D/daq_2Dviewer_Thorlabs_TSI.py
pymodaq_plugins_thorlabs/daq_viewer_plugins/plugins_ND/__init__.py
pymodaq_plugins_thorlabs/hardware/__init__.py
pymodaq_plugins_thorlabs/hardware/ccsxxx.py
pymodaq_plugins_thorlabs/hardware/daq_move_servocube_abstract.py
pymodaq_plugins_thorlabs/hardware/kinesis.py
pymodaq_plugins_thorlabs/hardware/powermeter.py
pymodaq_plugins_thorlabs/resources/__init__.py
pymodaq_plugins_thorlabs/resources/config_template.toml
pymodaq_plugins_thorlabs-5.0.0.dist-info/METADATA
pymodaq_plugins_thorlabs-5.0.0.dist-info/WHEEL
pymodaq_plugins_thorlabs-5.0.0.dist-info/entry_points.txt
pymodaq_plugins_thorlabs-5.0.0.dist-info/licenses/LICENSE
pymodaq_plugins_thorlabs-5.0.0.dist-info/RECORD
