Metadata-Version: 2.4
Name: pymodaq_plugins_thorlabs
Version: 5.0.0
Summary: Set of PyMoDAQ plugins for instruments from Thorlabs (Kinesis K10CR1 (stepper rotation actuator), Kinesis Flipper, Kinesis KSP100, DCx camera...)
Project-URL: Homepage, https://pymodaq.cnrs.fr
Project-URL: Documentation , https://pymodaq.cnrs.fr
Project-URL: Repository , https://github.com/PyMoDAQ/pymodaq_plugins_thorlabs
Author-email: Sébastien Weber <sebastien.weber@cemes.fr>
Maintainer-email: Sébastien Weber <sebastien.weber@cemes.fr>
License: The MIT License (MIT)
License-File: LICENSE
Classifier: Development Status :: 5 - Production/Stable
Classifier: Intended Audience :: Science/Research
Classifier: License :: OSI Approved :: MIT License
Classifier: Natural Language :: English
Classifier: Operating System :: OS Independent
Classifier: Programming Language :: Python :: 3.8
Classifier: Programming Language :: Python :: 3.9
Classifier: Programming Language :: Python :: 3.10
Classifier: Programming Language :: Python :: 3.11
Classifier: Topic :: Scientific/Engineering :: Human Machine Interfaces
Classifier: Topic :: Scientific/Engineering :: Visualization
Classifier: Topic :: Software Development :: Libraries :: Python Modules
Classifier: Topic :: Software Development :: User Interfaces
Requires-Python: >=3.8
Requires-Dist: elliptec
Requires-Dist: instrumental-lib
Requires-Dist: nicelib
Requires-Dist: opencv-python
Requires-Dist: pylablib==1.4.1
Requires-Dist: pymodaq-utils
Requires-Dist: pymodaq>=5.0.0
Requires-Dist: pythonnet
Requires-Dist: pywin32
